[{"date": "2018-10-26", "company_name": "四川省通信产业服务有限公司"}, {"date": "2018-10-26", "company_name": "中山东菱威力电器有限公司"}, {"date": "2018-10-26", "company_name": "美迪斯电梯有限公司"}, {"date": "2018-10-26", "company_name": "成都市锦江区明宇豪雅饭店有限公司"}, {"date": "2018-10-26", "company_name": "北京天创盛世数码科技有限公司"}, {"date": "2018-10-26", "company_name": "南国置业股份有限公司"}, {"date": "2018-10-25", "company_name": "中国石油天然气股份有限公司新疆油田分公..."}, {"date": "2018-10-25", "company_name": "深圳市一博科技有限公司"}, {"date": "2018-10-25", "company_name": "四川阳光盛美教育科技有限公司"}, {"date": "2018-10-25", "company_name": "成都大汇科技集团有限公司"}, {"date": "2018-10-25", "company_name": "纳爱斯集团有限公司成都分公司"}, {"date": "2018-10-25", "company_name": "成都珍岛信息技术有限公司"}, {"date": "2018-10-25", "company_name": "成都中科宇图科技有限公司"}, {"date": "2018-10-24", "company_name": "东华软件股份公司"}, {"date": "2018-10-24", "company_name": "上海德拓信息技术股份 有限公司"}, {"date": "2018-10-24", "company_name": "中国水利水电第十一工程局有限公司"}, {"date": "2018-10-24", "company_name": "鲜生活冷链物流有限公司"}, {"date": "2018-10-24", "company_name": "成都地铁运营有限公司"}, {"date": "2018-10-24", "company_name": "音泰思计算机技术(成都)有限公司"}, {"date": "2018-10-24", "company_name": "北京京东金融控股有限公司"}, {"date": "2018-10-23", "company_name": "中国葛洲坝集团电力有限责任公司"}, {"date": "2018-10-23", "company_name": "重庆金康动力新能源有限公司"}, {"date": "2018-10-23", "company_name": "成都国美大数据科技有限公司"}, {"date": "2018-10-23", "company_name": "四川捷祥医疗器械有限公司"}, {"date": "2018-10-23", "company_name": "全友家私有限公司"}, {"date": "2018-10-23", "company_name": "四川苏宁易购销售有限公司"}, {"date": "2018-10-23", "company_name": "浙江吉利控股集团有限公司"}, {"date": "2018-10-22", "company_name": "广东省电信规划设计院有限公司"}, {"date": "2018-10-22", "company_name": "成都世豪资产经营管理有限公司"}, {"date": "2018-10-22", "company_name": "新疆天池能源有限责任公司"}, {"date": "2018-10-22", "company_name": "雅马哈发动机（厦门）信息系统有限公司"}, {"date": "2018-10-22", "company_name": "广东通宇通讯股份有限公司"}, {"date": "2018-10-22", "company_name": "北京华拓金融服务外包有限公司"}, {"date": "2018-10-21", "company_name": "攀枝花市仁和区人力资源和社会保障局"}, {"date": "2018-10-19", "company_name": "成都龙光二环高速公路有限公司"}, {"date": "2018-10-19", "company_name": "四川剑南春（集团）有限公司"}, {"date": "2018-10-19", "company_name": "深圳市望尘科技有限公司"}, {"date": "2018-10-19", "company_name": "杭州安恒信息技术股份有限公司"}, {"date": "2018-10-19", "company_name": "北京中公教育科技股份有限公司四川分公司"}, {"date": "2018-10-18", "company_name": "广州兴森快捷电路科技有限公司"}, {"date": "2018-10-18", "company_name": "贵州航天电子科技有限公司"}, {"date": "2018-10-18", "company_name": "重庆翊宝智慧电子装置有限公司"}, {"date": "2018-10-18", "company_name": "成都万学海文教育科技有限公司"}, {"date": "2018-10-18", "company_name": "中山市欧帝尔电器照明有限公司"}, {"date": "2018-10-18", "company_name": "成都辛和品牌营销策划有限公司"}, {"date": "2018-10-18", "company_name": "杭州圆通货运航空有限公司"}, {"date": "2018-10-18", "company_name": "兰舍硅藻新材料有限公司"}, {"date": "2018-10-18", "company_name": "成都冠培教育咨询有限公司"}, {"date": "2018-10-17", "company_name": "成都企钧工业技术有限公司"}, {"date": "2018-10-17", "company_name": "维塔士电脑软件（成都）有限公司"}, {"date": "2018-10-17", "company_name": "深圳市数存科技有限公司"}, {"date": "2018-10-17", "company_name": "安徽新华教育集团有限公司"}, {"date": "2018-10-17", "company_name": "中国联合网络通信有限公司四川省分公司"}, {"date": "2018-10-17", "company_name": "中外运空运发展股份有限公司西南分公司"}, {"date": "2018-10-17", "company_name": "成都博智维讯信息技术股份有限公司"}, {"date": "2018-10-16", "company_name": "深圳富泰宏精密工业有限公司"}, {"date": "2018-10-16", "company_name": "东莞市盛雄激光设备有限公司"}, {"date": "2018-10-16", "company_name": "中国工商银行股份有限公司成都分行"}, {"date": "2018-10-16", "company_name": "国电南京自动化股份有限公司"}, {"date": "2018-10-16", "company_name": "成都路行通信息技术有限公司"}, {"date": "2018-10-16", "company_name": "成都交大光芒科技股份有限公司"}, {"date": "2018-10-16", "company_name": "成都星辰瀑布通信技术有限公司"}, {"date": "2018-10-15", "company_name": "四川天府江东科技有限公司"}, {"date": "2018-10-15", "company_name": "江苏永鼎股份有限公司"}, {"date": "2018-10-15", "company_name": "成都芯源系统有限公司"}, {"date": "2018-10-15", "company_name": "四川拉赫希网络科技有限公司"}, {"date": "2018-10-15", "company_name": "神州数码信息服务股份有限公司"}, {"date": "2018-10-12", "company_name": "福建博思软件股份有限公司"}, {"date": "2018-10-12", "company_name": "瑞声光电科技（常州）有限公司"}, {"date": "2018-10-12", "company_name": "成都万创科技有限责任公司"}, {"date": "2018-10-12", "company_name": "成都微银合创科技有限公司"}, {"date": "2018-10-12", "company_name": "四川倍发科技有限公司"}, {"date": "2018-10-11", "company_name": "成都聚美优品科技有限公司"}, {"date": "2018-10-11", "company_name": "川开电气有限公司"}, {"date": "2018-10-11", "company_name": "成都安可信电子股份有限公司"}, {"date": "2018-10-11", "company_name": "中交第三公路工程局有限公司"}, {"date": "2018-10-11", "company_name": "新航道（北京）管理咨询有限公司"}, {"date": "2018-10-10", "company_name": "宇芯（成都）集成电路封装测试有限公司"}, {"date": "2018-10-10", "company_name": "税友软件集团股份有限公司"}, {"date": "2018-10-10", "company_name": "江苏雷科防务科技股份有限公司"}, {"date": "2018-10-10", "company_name": "中科创达软件股份有限公司成都分公司"}, {"date": "2018-10-10", "company_name": "北京超图软件股份有限公司"}, {"date": "2018-10-10", "company_name": "杭州娃哈哈集团有限公司"}, {"date": "2018-10-09", "company_name": "鸿富锦精密电子（成都）有限公司"}, {"date": "2018-10-09", "company_name": "成都智明达电子股份有限公司"}, {"date": "2018-10-09", "company_name": "广东安居宝数码科技股份有限公司"}, {"date": "2018-10-09", "company_name": "四川我要去哪科技股份有限公司"}, {"date": "2018-10-09", "company_name": "成都珍岛信息技术有限公司"}, {"date": "2018-10-09", "company_name": "哈尔滨安天科技集团股份有限公司"}, {"date": "2018-10-09", "company_name": "倍睿软件（成都）有限公司"}, {"date": "2018-09-30", "company_name": "成都航空有限公司"}, {"date": "2018-09-29", "company_name": "中国化学工程第七建设有限公司"}, {"date": "2018-09-29", "company_name": "西安华腾微波有限责任公司"}, {"date": "2018-09-29", "company_name": "四川久远银海软件股份有限公司"}, {"date": "2018-09-29", "company_name": "上海埃林哲软件系统股份有限公司"}, {"date": "2018-09-29", "company_name": "中航材导航技术（北京）有限公司"}, {"date": "2018-09-28", "company_name": "成都开方数据科技有限公司"}, {"date": "2018-09-28", "company_name": "中通服创立信息科技有限责任公司"}, {"date": "2018-09-28", "company_name": "杭州士兰集成电路有限公司"}, {"date": "2018-09-28", "company_name": "上海目迩电子科技有限公司"}, {"date": "2018-09-28", "company_name": "西安博彦信息技术有限公司"}, {"date": "2018-09-28", "company_name": "四川现代汽车有限公司"}, {"date": "2018-09-28", "company_name": "中国电信股份有限公司四川分公司"}, {"date": "2018-09-27", "company_name": "北京中公未来教育咨询有限公司四川分公司"}, {"date": "2018-09-27", "company_name": "深圳市荣源木业有限公司"}, {"date": "2018-09-27", "company_name": "成都市极米科技有限公司"}, {"date": "2018-09-27", "company_name": "北京华如科技股份有限公司"}, {"date": "2018-09-27", "company_name": "宁波群志光电有限公司"}, {"date": "2018-09-27", "company_name": "四川凯盛经略投资咨询有限公司"}, {"date": "2018-09-26", "company_name": "通威太阳能（成都）有限公司"}, {"date": "2018-09-26", "company_name": "江苏创源电子有限公司"}, {"date": "2018-09-26", "company_name": "成都龙湖物业服务有限公司"}, {"date": "2018-09-26", "company_name": "成都振芯科技股份有限公司"}, {"date": "2018-09-26", "company_name": "四川弈新实业有限公司"}, {"date": "2018-09-26", "company_name": "华润置地（成都）物业服务有限公司"}, {"date": "2018-09-25", "company_name": "中铁二局集团有限公司"}, {"date": "2018-09-25", "company_name": "成都馨尹房地产营销策划有限公司"}, {"date": "2018-09-25", "company_name": "宜宾丰川动力科技有限公司"}, {"date": "2018-09-25", "company_name": "成都埃克森尔科技有限公司"}, {"date": "2018-09-25", "company_name": "成都卓杭网络科技股份有限公司"}, {"date": "2018-09-21", "company_name": "深圳市海勤科技有限公司"}, {"date": "2018-09-21", "company_name": "深圳天源迪科信息技术有限公司成都分公司"}, {"date": "2018-09-21", "company_name": "成都启英泰伦科技有限公司"}, {"date": "2018-09-21", "company_name": "成都亿泽房地产经纪有限公司"}, {"date": "2018-09-21", "company_name": "中国民航信息网络股份有限公司重庆分公司"}, {"date": "2018-09-20", "company_name": "成都拓尔思信息技术有限公司"}, {"date": "2018-09-20", "company_name": "安徽四创电子股份有限公司"}, {"date": "2018-09-20", "company_name": "软通动力信息技术（集团）有限公司"}, {"date": "2018-09-20", "company_name": "中国移动通信集团四川有限公司"}, {"date": "2018-09-20", "company_name": "成都唐源电气股份有限公司"}, {"date": "2018-09-20", "company_name": "成都盟升电子技术股份有限公司"}, {"date": "2018-09-20", "company_name": "成都帝标智能家居有限公司"}, {"date": "2018-09-20", "company_name": "四川大能科技有限公司"}, {"date": "2018-09-19", "company_name": "成都国铁电气设备有限公司"}, {"date": "2018-09-19", "company_name": "成都创信华通信息技术有限公司"}, {"date": "2018-09-19", "company_name": "上海商泰汽车信息系统有限公司"}, {"date": "2018-09-19", "company_name": "华润微电子（重庆）有限公司"}, {"date": "2018-09-19", "company_name": "泸州翰林辅教中心"}, {"date": "2018-09-18", "company_name": "成都国科微电子有限公司"}, {"date": "2018-09-18", "company_name": "北京中公未来教育咨询有限公司四川分公司"}, {"date": "2018-09-18", "company_name": "杭州海康威视数字技术股份有限公司成都分..."}, {"date": "2018-09-18", "company_name": "四川苏宁易购销售有限公司"}, {"date": "2018-09-18", "company_name": "深圳市风云实业有限公司成都分公司"}, {"date": "2018-09-18", "company_name": "成都筑巢电子商务有限公司"}, {"date": "2018-09-18", "company_name": "贵州航天特种车有限责任公司"}, {"date": "2018-09-18", "company_name": "成都天奥电子股份有限公司"}, {"date": "2018-09-17", "company_name": "超凡知识产权服务有限公司"}, {"date": "2018-09-17", "company_name": "北京童程童美科技有限公司"}, {"date": "2018-09-17", "company_name": "成都余香科技股份有限公司"}, {"date": "2018-09-17", "company_name": "成都新大瀚人力资源管理有限公司"}, {"date": "2018-09-17", "company_name": "葛洲坝集团机电建设有限公司"}, {"date": "2018-09-14", "company_name": "成都视达科信息技术有限公司"}, {"date": "2018-09-14", "company_name": "深圳市国人射频通信有限公司"}, {"date": "2018-09-14", "company_name": "中国电子系统工程第三建设有限公司"}, {"date": "2018-09-14", "company_name": "深圳市蓝凌软件股份有限公司成都分公司"}, {"date": "2018-09-13", "company_name": "四川准达信息技术有限公司"}, {"date": "2018-09-13", "company_name": "思特沃克软件技术（成都）有限公司"}, {"date": "2018-09-13", "company_name": "北京亚控科技发展有限公司"}, {"date": "2018-09-13", "company_name": "成都梓华科技有限公司"}, {"date": "2018-09-12", "company_name": "松翰科技（成都）有限公司"}, {"date": "2018-09-12", "company_name": "中国核工业二三建设有限公司"}, {"date": "2018-09-12", "company_name": "希望森兰科技股份有限公司"}, {"date": "2018-09-12", "company_name": "四川长虹电子控股集团有限公司"}, {"date": "2018-09-11", "company_name": "成都三泰控股集团股份有限公司"}, {"date": "2018-09-11", "company_name": "浙江大华技术股份有限公司"}, {"date": "2018-09-11", "company_name": "先进科技（中国）有限公司"}, {"date": "2018-09-10", "company_name": "成都市一览扎堆信息科技有限公司"}, {"date": "2018-09-10", "company_name": "四川中电启明星信息技术有限公司"}, {"date": "2018-09-10", "company_name": "四川航空股份有限公司"}, {"date": "2018-06-13", "company_name": "德州仪器半导体制造（成都）有限公司"}, {"date": "2018-05-24", "company_name": "金山珠海西山居有限公司"}, {"date": "2018-05-18", "company_name": "成都宜君企业管理有限公司"}, {"date": "2018-05-17", "company_name": "北京中公未来教育咨询有限公司四川分公司"}, {"date": "2018-05-16", "company_name": "泸州金能移动能源科技有限公司"}, {"date": "2018-05-14", "company_name": "唐山市广播电视大学"}, {"date": "2018-05-02", "company_name": "万达信息股份有限公司"}, {"date": "2018-04-27", "company_name": "厦门航空股份有限公司"}, {"date": "2018-04-27", "company_name": "成都智通恒达科技有限公司"}, {"date": "2018-04-26", "company_name": "成都盛科信息技术有限公司"}, {"date": "2018-04-24", "company_name": "上海优尔蓝信息科技股份有限公司"}, {"date": "2018-04-24", "company_name": "四川旭普信息发展有限公司"}, {"date": "2018-04-20", "company_name": "青川县2018年上半年引进高层次人才"}, {"date": "2018-04-19", "company_name": "维塔士电脑软件（成都）有限公司"}, {"date": "2018-04-17", "company_name": "成都先进功率半导体股份有限公司"}, {"date": "2018-04-17", "company_name": "东华软件股份公司"}, {"date": "2018-04-13", "company_name": "合盛硅业（泸州）有限公司"}, {"date": "2018-04-13", "company_name": "四川超凡知识产权服务股份有限公司"}, {"date": "2018-04-12", "company_name": "新蛋科技（成都）有限公司"}, {"date": "2018-04-10", "company_name": "西藏专用通信局"}, {"date": "2018-04-10", "company_name": "成都红剑科技有限公司"}, {"date": "2018-04-10", "company_name": "重庆传音科技有限公司"}, {"date": "2018-04-09", "company_name": "中软国际科技服务有限公司"}, {"date": "2018-04-08", "company_name": "成都中建材光电材料有限公司"}, {"date": "2018-04-08", "company_name": "成都拓尔思信息技术有限公司"}, {"date": "2018-04-03", "company_name": "建滔敷铜板（深圳）有限公司"}, {"date": "2018-04-02", "company_name": "上海德拓信息技术股份 有限公司"}, {"date": "2018-04-02", "company_name": "四川准达信息技术有限公司"}, {"date": "2018-04-02", "company_name": "上海英科实业有限公司"}, {"date": "2018-03-30", "company_name": "四川军工人力资源责任有限公司绵阳分公司"}, {"date": "2018-03-30", "company_name": "成都必控科技股份有限公司"}, {"date": "2018-03-29", "company_name": "成都国科微电子有限公司"}, {"date": "2018-03-29", "company_name": "软通动力成都分公司"}, {"date": "2018-03-29", "company_name": "成都川越教育服务有限责任公司"}, {"date": "2018-03-29", "company_name": "佛山市博亿达进出口有限公司"}, {"date": "2018-03-28", "company_name": "北京中公未来教育咨询有限公司四川分公司"}, {"date": "2018-03-28", "company_name": "西部航空责任有限公司"}, {"date": "2018-03-28", "company_name": "纬创资通（成都）有限公司"}, {"date": "2018-03-28", "company_name": "东莞市福德自动化科技有限公司"}, {"date": "2018-03-27", "company_name": "西藏某政法机关"}, {"date": "2018-03-27", "company_name": "四川省对外文化交流中心"}, {"date": "2018-03-27", "company_name": "中共远安县委组织部"}, {"date": "2018-03-27", "company_name": "成都美景舒适家居有限公司"}, {"date": "2018-03-27", "company_name": "四川和芯微电子股份有限公司"}, {"date": "2018-03-27", "company_name": "中软国际科技服务有限公司"}, {"date": "2018-03-26", "company_name": "成都路维光电有限公司"}, {"date": "2018-03-26", "company_name": "翔耀电子（深圳）有限公司"}, {"date": "2018-03-23", "company_name": "广东三维家信息技术有限公司"}, {"date": "2018-03-23", "company_name": "四川龙浩飞行驾驶培训有限公司"}, {"date": "2018-03-23", "company_name": "平安国际融资租赁有限公司"}, {"date": "2018-03-23", "company_name": "成都新都区极客数学帮培训学校"}, {"date": "2018-03-22", "company_name": "TCL海外电子（惠州）有限公司"}, {"date": "2018-03-22", "company_name": "北京睿智融科控股股份有限公司"}, {"date": "2018-03-22", "company_name": "软通动力成都分公司"}, {"date": "2018-03-21", "company_name": "北京中公未来教育咨询有限公司四川分公司"}, {"date": "2018-03-21", "company_name": "北京中公未来教育咨询有限公司四川分公司"}, {"date": "2018-03-21", "company_name": "中铁十五局集团股份有限公司"}, {"date": "2018-03-21", "company_name": "成都新易盛通信技术股份有限公司"}, {"date": "2018-03-21", "company_name": "南京烽火星空通信发展有限公司"}, {"date": "2018-03-20", "company_name": "成都中电熊猫显示科技有限公司"}, {"date": "2018-03-19", "company_name": "海南省省直机关"}, {"date": "2018-03-19", "company_name": "四川赛狄信息技术股份公司"}, {"date": "2018-03-19", "company_name": "瑞声光电科技（常州）有限公司"}, {"date": "2018-03-16", "company_name": "通威太阳能（成都）有限公司"}, {"date": "2018-03-16", "company_name": "四川康盛企业管理有限公司"}, {"date": "2018-03-16", "company_name": "成都航空有限公司"}, {"date": "2018-03-15", "company_name": "四川我要去哪科技股份有限公司"}, {"date": "2018-03-15", "company_name": "中国电建集团四川工程有限公司"}, {"date": "2018-03-14", "company_name": "四川航空股份有限公司"}, {"date": "2018-03-14", "company_name": "成都芯源系统有限公司"}, {"date": "2018-03-14", "company_name": "北京飞机维修工程有限公司"}, {"date": "2018-03-13", "company_name": "成都星辰瀑布通信技术有限公司"}, {"date": "2018-03-13", "company_name": "成都博智维讯信息技术股份有限公司"}, {"date": "2018-03-12", "company_name": "武汉某政法机关"}, {"date": "2018-03-12", "company_name": "鸿富锦精密电子（成都）有限公司"}, {"date": "2017-12-20", "company_name": "深圳即有信息科技有限公司成都分公司"}, {"date": "2017-12-12", "company_name": "成都智云汇通科技有限公司"}, {"date": "2017-12-07", "company_name": "重庆中电自能科技有限公司"}, {"date": "2017-12-05", "company_name": "绵阳京东方光电科技有限公司"}, {"date": "2017-12-01", "company_name": "成都云智天下科技有限公司"}, {"date": "2017-12-01", "company_name": "成都安德诺晟人力资源有限公司"}, {"date": "2017-12-01", "company_name": "信利半导体有限公司"}, {"date": "2017-11-30", "company_name": "成都新洲航空设备有限责任公司"}, {"date": "2017-11-29", "company_name": "厦门纵横集团股份有限公司"}, {"date": "2017-11-29", "company_name": "成都中电熊猫显示科技有限公司"}, {"date": "2017-11-28", "company_name": "四川众望安全环保技术咨询有限公司"}, {"date": "2017-11-24", "company_name": "润建通信股份有限公司广东分公司"}, {"date": "2017-11-24", "company_name": "四川天府银行股份有限公司"}, {"date": "2017-11-23", "company_name": "武汉华工激光工程有限责任公司"}, {"date": "2017-11-23", "company_name": "福州航空有限公司"}, {"date": "2017-11-22", "company_name": "南京唯实科技有限公司"}, {"date": "2017-11-22", "company_name": "北京中公未来教育咨询有限公司四川分公司"}, {"date": "2017-11-22", "company_name": "广东鸿特普惠信息服务有限公司"}, {"date": "2017-11-21", "company_name": "北京京东金融控股有限公司"}, {"date": "2017-11-21", "company_name": "三和盛电子制品（东莞）有限公司"}, {"date": "2017-11-21", "company_name": "鸿富锦精密电子（成都）有限公司"}, {"date": "2017-11-20", "company_name": "深圳市德仓科技有限公司"}, {"date": "2017-11-20", "company_name": "成都市臻爱宠物医院有限公司"}, {"date": "2017-11-20", "company_name": "昊盈信息技术（成都）有限公司"}, {"date": "2017-11-17", "company_name": "南京烽火星空通信发展有限公司"}, {"date": "2017-11-17", "company_name": "北京云创世联科技股份有限公司"}, {"date": "2017-11-16", "company_name": "中粮食品营销有限公司（世界五百强企业）"}, {"date": "2017-11-16", "company_name": "江西航空有限公司"}, {"date": "2017-11-16", "company_name": "成都沃达惠康科技股份有限公司"}, {"date": "2017-11-16", "company_name": "凉山雷波县供电局"}, {"date": "2017-11-16", "company_name": "仟之游软件科技(成都)有限公司"}, {"date": "2017-11-15", "company_name": "中通服软件科技有限公司上海分公司"}, {"date": "2017-11-15", "company_name": "平安普惠企业管理有限公司四川分公司"}, {"date": "2017-11-15", "company_name": "上海澳华光电内窥镜有限公司"}, {"date": "2017-11-15", "company_name": "成都启臣微电子股份有限公司"}, {"date": "2017-11-15", "company_name": "成都东方盛行电子有限责任公司"}, {"date": "2017-11-14", "company_name": "宁波盛威卓越安全设备有限公司"}, {"date": "2017-11-14", "company_name": "四川军工人力资源责任有限公司绵阳分公司"}, {"date": "2017-11-14", "company_name": "成都道森能源有限公司"}, {"date": "2017-11-14", "company_name": "润建通信股份有限公司"}, {"date": "2017-11-14", "company_name": "航天恒星科技有限公司"}, {"date": "2017-11-13", "company_name": "四川雅化实业集团股份有限公司"}, {"date": "2017-11-13", "company_name": "北京融和友信科技股份有限公司"}, {"date": "2017-11-13", "company_name": "成都华西公用医疗信息服务有限公司"}, {"date": "2017-11-13", "company_name": "四川雅化实业集团股份有限公司"}, {"date": "2017-11-13", "company_name": "宁波盛威卓越安全设备有限公司"}, {"date": "2017-11-10", "company_name": "深圳市迪比科电子科技有限公司"}, {"date": "2017-11-10", "company_name": "杭州西奥电梯有限公司"}, {"date": "2017-11-10", "company_name": "四川天邑康和通信股份有限公司"}, {"date": "2017-11-09", "company_name": "成都巴索软件有限公司"}, {"date": "2017-11-09", "company_name": "成都百城投资有限责任公司"}, {"date": "2017-11-09", "company_name": "成都华唯科技股份有限公司"}, {"date": "2017-11-09", "company_name": "中金支付有限公司"}, {"date": "2017-11-08", "company_name": "云南祥鹏航空有限责任公司"}, {"date": "2017-11-08", "company_name": "成都网安科技发展有限公司"}, {"date": "2017-11-08", "company_name": "河北博岳通信技术股份有限公司"}, {"date": "2017-11-08", "company_name": "先进科技（中国）有限公司"}, {"date": "2017-11-07", "company_name": "华通电脑(重庆)有限公司"}, {"date": "2017-11-07", "company_name": "四川超凡知识产权服务股份有限公司"}, {"date": "2017-11-07", "company_name": "张家港万蓬木业有限公司"}, {"date": "2017-11-07", "company_name": "成都新大瀚人力资源管理有限公司"}, {"date": "2017-11-07", "company_name": "安踏体育用品集团有限公司"}, {"date": "2017-11-07", "company_name": "天马微电子股份有限公司"}, {"date": "2017-11-07", "company_name": "成都盼达汽车租赁有限公司"}, {"date": "2017-11-06", "company_name": "成都军械厂"}, {"date": "2017-11-06", "company_name": "成都万创科技有限责任公司"}, {"date": "2017-11-06", "company_name": "四川省对外文化交流中心"}, {"date": "2017-11-06", "company_name": "四川智捷利机器人科技有限公司"}, {"date": "2017-11-06", "company_name": "深圳市汇合发展有限公司成都分公司"}, {"date": "2017-11-05", "company_name": "讯芯电子科技(中山)有限公司"}, {"date": "2017-11-03", "company_name": "成都市肆零肆网络科技有限公司"}, {"date": "2017-11-03", "company_name": "成都第二梦科技有限公司"}, {"date": "2017-11-03", "company_name": "久盛地板有限公司"}, {"date": "2017-11-03", "company_name": "世硕电子（昆山）有限公司"}, {"date": "2017-11-02", "company_name": "仁宝电脑（成都）有限公司"}, {"date": "2017-11-02", "company_name": "遂宁银行股份有限公司-招聘信息科技岗等..."}, {"date": "2017-11-02", "company_name": "上海安鲜达物流科技有限公司"}, {"date": "2017-11-02", "company_name": "北京科银京成技术有限公司"}, {"date": "2017-11-01", "company_name": "四川航天电液控制有限公司"}, {"date": "2017-11-01", "company_name": "南京通达海信息技术有限公司"}, {"date": "2017-11-01", "company_name": "四川鲜女果生态农业有限公司"}, {"date": "2017-11-01", "company_name": "环宇集团浙江高科股份有限公司"}, {"date": "2017-11-01", "company_name": "成都有明堂互动科技有限公司"}, {"date": "2017-10-31", "company_name": "番禺得意精密电子工业有限公司"}, {"date": "2017-10-31", "company_name": "成都奥特为通讯有限公司"}, {"date": "2017-10-30", "company_name": "成都巴索软件有限公司"}, {"date": "2017-10-30", "company_name": "成都八千翼网络科技有限公司"}, {"date": "2017-10-30", "company_name": "成都游戏汇企业管理有限公司"}, {"date": "2017-10-30", "company_name": "四川德惠商业股份有限公司"}, {"date": "2017-10-28", "company_name": "北京爱博精电科技有限公司"}, {"date": "2017-10-27", "company_name": "七色纺商业连锁有限公司"}, {"date": "2017-10-27", "company_name": "台晶(重庆)电子有限公司"}, {"date": "2017-10-27", "company_name": "成都欧盛电子产品有限公司"}, {"date": "2017-10-26", "company_name": "深圳市华云中盛科技有限公司"}, {"date": "2017-10-26", "company_name": "深圳市一博科技有限公司"}, {"date": "2017-10-26", "company_name": "深圳市中钞信达金融科技有限公司"}, {"date": "2017-10-26", "company_name": "成都泰美克晶体技术有限公司"}, {"date": "2017-10-26", "company_name": "上海汉得信息技术股份有限公司"}, {"date": "2017-10-26", "company_name": "成都龙湖物业服务有限公司"}, {"date": "2017-10-26", "company_name": "绵阳市有芯电子有限公司"}, {"date": "2017-10-25", "company_name": "四川享宇金信金融服务外包有限公司"}, {"date": "2017-10-25", "company_name": "四川盛和电器有限公司"}, {"date": "2017-10-25", "company_name": "四川弈新实业有限公司"}, {"date": "2017-10-25", "company_name": "安得智联科技股份有限公司"}, {"date": "2017-10-24", "company_name": "松翰科技（成都）有限公司"}, {"date": "2017-10-24", "company_name": "四川帝王洁具股份有限公司"}, {"date": "2017-10-24", "company_name": "成都国铁电气设备有限公司"}, {"date": "2017-10-24", "company_name": "成都新都区极客数学帮培训学校"}, {"date": "2017-10-24", "company_name": "成都中科宇图科技有限公司"}, {"date": "2017-10-23", "company_name": "成都安可信电子股份有限公司"}, {"date": "2017-10-23", "company_name": "四川成创世纪实业有限公司"}, {"date": "2017-10-23", "company_name": "广东长虹日电科技有限公司"}, {"date": "2017-10-23", "company_name": "成都芯源系统有限公司"}, {"date": "2017-10-23", "company_name": "川开电气有限公司"}, {"date": "2017-10-23", "company_name": "广州立白企业集团有限公司"}, {"date": "2017-10-20", "company_name": "宁波创元信息科技有限公司"}, {"date": "2017-10-20", "company_name": "重庆昊恩健康产业研究中心"}, {"date": "2017-10-20", "company_name": "四川锦美环保股份有限公司"}, {"date": "2017-10-20", "company_name": "华讯方舟科技有限公司"}, {"date": "2017-10-20", "company_name": "上海珍岛信息技术有限公司有限责任公司"}, {"date": "2017-10-20", "company_name": "中山联合光电科技股份有限公司"}, {"date": "2017-10-19", "company_name": "成都启英泰伦科技有限公司"}, {"date": "2017-10-19", "company_name": "纬创资通（成都）有限公司"}, {"date": "2017-10-19", "company_name": "四川省通信产业服务有限公司"}, {"date": "2017-10-19", "company_name": "四川弈新实业有限公司"}, {"date": "2017-10-19", "company_name": "四川丹秋教育管理咨询有限公司"}, {"date": "2017-10-19", "company_name": "维塔士电脑软件（成都）有限公司"}, {"date": "2017-10-18", "company_name": "深圳市豪恩科技集团股份有限公司"}, {"date": "2017-10-18", "company_name": "北京中公未来教育咨询有限公司四川分公司"}, {"date": "2017-10-18", "company_name": "北京中公未来教育咨询有限公司四川分公司"}, {"date": "2017-10-18", "company_name": "全友家私有限公司"}, {"date": "2017-10-18", "company_name": "成都市映潮科技股份有限公司"}, {"date": "2017-10-18", "company_name": "成都中电熊猫显示科技有限公司"}, {"date": "2017-10-17", "company_name": "意尔康股份有限公司"}, {"date": "2017-10-17", "company_name": "北京中公未来教育咨询有限公司四川分公司"}, {"date": "2017-10-17", "company_name": "四川迅游网络科技股份有限公司"}, {"date": "2017-10-17", "company_name": "海南航空学校有限责任公司宜昌分公司"}, {"date": "2017-10-17", "company_name": "成都兴邦咨询有限公司"}, {"date": "2017-10-17", "company_name": "成都新易盛通信技术股份有限公司"}, {"date": "2017-10-16", "company_name": "中国联合网络通信有限公司四川省分公司"}, {"date": "2017-10-16", "company_name": "安徽四创电子股份有限公司"}, {"date": "2017-10-16", "company_name": "成都市兴蓉集团有限公司"}, {"date": "2017-10-16", "company_name": "软通动力成都分公司"}, {"date": "2017-10-16", "company_name": "成都九江伟业科技有限公司"}, {"date": "2017-10-13", "company_name": "昌碩科技（上海）有限公司"}, {"date": "2017-10-13", "company_name": "厦门航空有限公司"}, {"date": "2017-10-13", "company_name": "北京国遥新天地信息技术有限公司"}, {"date": "2017-10-13", "company_name": "神州数码信息服务股份有限公司"}, {"date": "2017-10-13", "company_name": "深圳航空有限责任公司"}, {"date": "2017-10-12", "company_name": "上海埃林哲软件系统股份有限公司"}, {"date": "2017-10-12", "company_name": "北京中公未来教育咨询有限公司四川分公司"}, {"date": "2017-10-12", "company_name": "易指生活（上海）科技股份有限公司"}, {"date": "2017-10-12", "company_name": "四川省宜宾普什集团有限公司"}, {"date": "2017-10-12", "company_name": "北京优炫软件股份有限公司"}, {"date": "2017-10-11", "company_name": "宏明电子科大新材料有限公司"}, {"date": "2017-10-11", "company_name": "北京华如科技股份有限公司"}]